kg_ingressnginx/__init__.py
kg_ingressnginx/builder.py
kg_ingressnginx/option.py
kg_ingressnginx/py.typed
kg_ingressnginx-0.8.0.dist-info/LICENSE
kg_ingressnginx-0.8.0.dist-info/METADATA
kg_ingressnginx-0.8.0.dist-info/WHEEL
kg_ingressnginx-0.8.0.dist-info/top_level.txt
kg_ingressnginx-0.8.0.dist-info/RECORD
